{"metadata": {"total": 8, "page": 0, "per_page": 20}, "results": [{"school.zip": "22903-2628", "location.lat": 38.035665, "location.lon": -78.503428, "school.name": "University of Virginia-Main Campus", "school.state": "VA", "id": 234076, "school.city": "Charlottesville"}, {"school.zip": "24501", "location.lat": 37.395135, "location.lon": -79.151518, "school.name": "Virginia University of Lynchburg", "school.state": "VA", "id": 234137, "school.city": "Lynchburg"}, {"school.zip": "23060", "location.lat": 37.64257, "location.lon": -77.563516, "school.name": "University of Phoenix-Virginia", "school.state": "VA", "id": 484765, "school.city": "Glen Allen"}, {"school.zip": "24293-4400", "location.lat": 36.971468, "location.lon": -82.558728, "school.name": "The University of Virginia's College at Wise", "school.state": "VA", "id": 233897, "school.city": "Wise"}, {"school.zip": "235131603", "location.lat": 0.0, "location.lon": 0.0, "school.name": "ECPI University-Culinary Institute of Virginia", "school.state": "VA", "id": 24893410, "school.city": "Norfolk"}, {"school.zip": "26726", "location.lat": 39.438323, "location.lon": -78.981441, "school.name": "Potomac State College of West Virginia University", "school.state": "WV", "id": 237701, "school.city": "Keyser"}, {"school.zip": "25801", "location.lat": 37.775924, "location.lon": -81.184072, "school.name": "West Virginia University Institute of Technology", "school.state": "WV", "id": 237950, "school.city": "Beckley"}, {"school.zip": "26506-8062", "location.lat": 39.654269, "location.lon": -79.957959, "school.name": "West Virginia University Hospital Departments of Rad Tech and Nutrition", "school.state": "WV", "id": 237905, "school.city": "Morgantown"}]}